crawl_two_num/__init__.py
crawl_two_num/two_num.py
CrawlTwoNum-0.0.1.dist-info/LICENSE
CrawlTwoNum-0.0.1.dist-info/METADATA
CrawlTwoNum-0.0.1.dist-info/WHEEL
CrawlTwoNum-0.0.1.dist-info/top_level.txt
CrawlTwoNum-0.0.1.dist-info/RECORD
