Metadata-Version: 2.1
Name: CrawlTwoNum
Version: 0.0.1
Summary: a common package
Home-page: https://github.com/zh-Juliet/CrawlTwoNum
Author: Juliet
Author-email: zh_juiet@163.com
License: UNKNOWN
Platform: UNKNOWN
Classifier: Programming Language :: Python :: 3
Classifier: License :: OSI Approved :: MIT License
Classifier: Operating System :: OS Independent
Requires-Python: >=3.6
